mcp_mapped_resource_lib/__init__.py
mcp_mapped_resource_lib/blob_id.py
mcp_mapped_resource_lib/cleanup.py
mcp_mapped_resource_lib/exceptions.py
mcp_mapped_resource_lib/hash.py
mcp_mapped_resource_lib/mime.py
mcp_mapped_resource_lib/path.py
mcp_mapped_resource_lib/storage.py
mcp_mapped_resource_lib/types.py
mcp_mapped_resource_lib-0.1.2.dist-info/METADATA
mcp_mapped_resource_lib-0.1.2.dist-info/WHEEL
mcp_mapped_resource_lib-0.1.2.dist-info/licenses/LICENSE
mcp_mapped_resource_lib-0.1.2.dist-info/RECORD
