Metadata-Version: 2.4
Name: mcp-mapped-resource-lib
Version: 0.1.2
Summary: Reusable utilities for MCP servers handling binary blob transfers through shared Docker volumes
Project-URL: Homepage, https://github.com/nickweedon/mcp_mapped_resource_lib
Project-URL: Repository, https://github.com/nickweedon/mcp_mapped_resource_lib
Project-URL: Issues, https://github.com/nickweedon/mcp_mapped_resource_lib/issues
Project-URL: Changelog, https://github.com/nickweedon/mcp_mapped_resource_lib/blob/main/CHANGELOG.md
Author-email: MCP Community <noreply@mcp.dev>
License: MIT
License-File: LICENSE
Keywords: binary-transfer,blob-storage,docker-volumes,mcp,model-context-protocol,resource-management
Classifier: Development Status :: 4 - Beta
Classifier: Intended Audience :: Developers
Classifier: License :: OSI Approved :: MIT License
Classifier: Operating System :: OS Independent
Classifier: Programming Language :: Python :: 3
Classifier: Programming Language :: Python :: 3.10
Classifier: Programming Language :: Python :: 3.11
Classifier: Programming Language :: Python :: 3.12
Classifier: Topic :: Internet :: WWW/HTTP
Classifier: Topic :: Software Development :: Libraries :: Python Modules
Classifier: Topic :: System :: Filesystems
Classifier: Typing :: Typed
Requires-Python: >=3.10
Requires-Dist: python-magic>=0.4.27
Provides-Extra: dev
Requires-Dist: mypy>=1.5.0; extra == 'dev'
Requires-Dist: pytest-asyncio>=0.21.0; extra == 'dev'
Requires-Dist: pytest-cov>=4.1.0; extra == 'dev'
Requires-Dist: pytest>=7.4.0; extra == 'dev'
Requires-Dist: ruff>=0.1.0; extra == 'dev'
